ipygraph/__init__.py
ipygraph/__main__.py
ipygraph/app.py
ipygraph/static/app.js
ipygraph/static/index.html
ipygraph/static/index_.html
ipygraph/static/style.css
ipygraph/static/vendor/particles.min.js
ipygraph-0.1.1.dist-info/licenses/LICENSE
ipygraph-0.1.1.dist-info/METADATA
ipygraph-0.1.1.dist-info/WHEEL
ipygraph-0.1.1.dist-info/entry_points.txt
ipygraph-0.1.1.dist-info/top_level.txt
ipygraph-0.1.1.dist-info/RECORD
