Metadata-Version: 2.4
Name: ipygraph
Version: 0.1.1
Summary: Desktop landing page for ipygraph – PyWebview + React with particles.js
Author-email: Your Name <you@example.com>
License: MIT
Requires-Python: >=3.8
License-File: LICENSE
Requires-Dist: pywebview
Dynamic: license-file
